pysignalclijsonrpc/__init__.py
pysignalclijsonrpc/api.py
pysignalclijsonrpc-25.9.0.dist-info/METADATA
pysignalclijsonrpc-25.9.0.dist-info/WHEEL
pysignalclijsonrpc-25.9.0.dist-info/licenses/LICENSE
pysignalclijsonrpc-25.9.0.dist-info/RECORD
