Metadata-Version: 2.4
Name: pysignalclijsonrpc
Version: 25.9.0
Summary: Python API client for signal-cli JSON-RPC
Author-email: Stefan Heitmüller <stefan.heitmueller@gmx.com>
License-File: LICENSE
Requires-Python: >=3.9
Requires-Dist: jmespath~=1.0
Requires-Dist: packaging>=24
Requires-Dist: python-magic~=0.4
Requires-Dist: requests~=2.32
